clickable/__init__.py
clickable/cli.py
clickable/command_utils.py
clickable/container.py
clickable/device.py
clickable/exceptions.py
clickable/logger.py
clickable/utils.py
clickable/version.py
clickable/builders/__init__.py
clickable/builders/base.py
clickable/builders/cmake.py
clickable/builders/custom.py
clickable/builders/go.py
clickable/builders/make.py
clickable/builders/pure.py
clickable/builders/qbs.py
clickable/builders/qmake.py
clickable/builders/rust.py
clickable/commands/__init__.py
clickable/commands/base.py
clickable/commands/build.py
clickable/commands/chain.py
clickable/commands/ci.py
clickable/commands/clean.py
clickable/commands/clean_images.py
clickable/commands/create.py
clickable/commands/desktop.py
clickable/commands/devices.py
clickable/commands/gdb.py
clickable/commands/gdbserver.py
clickable/commands/ide.py
clickable/commands/install.py
clickable/commands/launch.py
clickable/commands/log.py
clickable/commands/logs.py
clickable/commands/no_lock.py
clickable/commands/publish.py
clickable/commands/review.py
clickable/commands/run.py
clickable/commands/screenshots.py
clickable/commands/script.py
clickable/commands/setup.py
clickable/commands/shell.py
clickable/commands/test.py
clickable/commands/update_images.py
clickable/commands/writable_image.py
clickable/commands/docker/dbus_support.py
clickable/commands/docker/debug_gdb_support.py
clickable/commands/docker/debug_valgrind_support.py
clickable/commands/docker/docker_config.py
clickable/commands/docker/docker_support.py
clickable/commands/docker/go_support.py
clickable/commands/docker/multimedia_support.py
clickable/commands/docker/nvidia_support.py
clickable/commands/docker/rust_support.py
clickable/commands/docker/theme_support.py
clickable/commands/docker/webapp_support.py
clickable/commands/docker/nvidia/legacy_nvidia_support.py
clickable/commands/docker/nvidia/nvidia_support_since_docker_version_1903.py
clickable/commands/idedelegates/__init__.py
clickable_ut-8.7.0.dist-info/licenses/LICENSE
clickable_ut-8.7.0.dist-info/METADATA
clickable_ut-8.7.0.dist-info/WHEEL
clickable_ut-8.7.0.dist-info/entry_points.txt
clickable_ut-8.7.0.dist-info/top_level.txt
clickable_ut-8.7.0.dist-info/RECORD
