Metadata-Version: 2.4
Name: clickable-ut
Version: 8.7.0
Summary: Compile, build, and deploy Ubuntu Touch click packages all from the command line.
Home-page: https://clickable-ut.dev/
Author: Brian Douglass
License: GPL3
Project-URL: Documentation, https://clickable-ut.dev/en/latest/
Project-URL: Source, https://gitlab.com/clickable/clickable
Project-URL: Bug Tracker, https://gitlab.com/clickable/clickable/-/issues
Keywords: click ubuntu touch ubports
Classifier: Development Status :: 5 - Production/Stable
Classifier: Environment :: Console
Classifier: Intended Audience :: Developers
Classifier: License :: OSI Approved :: GNU General Public License v3 (GPLv3)
Classifier: Natural Language :: English
Classifier: Topic :: Software Development :: Build Tools
Classifier: Topic :: Software Development :: Code Generators
Classifier: Programming Language :: Python :: 3
Classifier: Programming Language :: Python :: 3.3
Classifier: Programming Language :: Python :: 3.4
Classifier: Programming Language :: Python :: 3.5
Classifier: Programming Language :: Python :: 3.6
Classifier: Programming Language :: Python :: 3.7
Classifier: Programming Language :: Python :: 3.8
License-File: LICENSE
Requires-Dist: cookiecutter
Requires-Dist: requests
Requires-Dist: PyYaml
Requires-Dist: jsonschema
Requires-Dist: argcomplete
Requires-Dist: watchdog
Dynamic: author
Dynamic: classifier
Dynamic: description
Dynamic: description-content-type
Dynamic: home-page
Dynamic: keywords
Dynamic: license
Dynamic: license-file
Dynamic: project-url
Dynamic: requires-dist
Dynamic: summary
